pg_ch_creator/__init__.py
pg_ch_creator/compile_dialect.py
pg_ch_creator/table_creator.py
pg_ch_creator/table_transformer.py
pg_ch_sync/__init__.py
pg_ch_sync/pg_ch_sync.py
pg_s3_ch/__init__.py
pg_s3_ch/pg_s3_ch.py
pg_s3_ch/sql_queries.py
pg_s3_ch/temp_table_creator_ch.py
pg_s3_ch_new_talenttech_oss-1.1.4.dist-info/LICENSE.txt
pg_s3_ch_new_talenttech_oss-1.1.4.dist-info/METADATA
pg_s3_ch_new_talenttech_oss-1.1.4.dist-info/WHEEL
pg_s3_ch_new_talenttech_oss-1.1.4.dist-info/top_level.txt
pg_s3_ch_new_talenttech_oss-1.1.4.dist-info/RECORD
