Metadata-Version: 2.1
Name: pg-s3-ch-new-talenttech-oss
Version: 1.1.4
Summary: TopMind PG S3 CH Helper
Home-page: https://github.com/severgroup-tt/topmind-commons
Author: Dmitry Utiralov
Author-email: d.utiralov@talenttech.ru
License: MIT
Classifier: Programming Language :: Python :: 3
Classifier: License :: OSI Approved :: MIT License
Classifier: Operating System :: OS Independent
Requires-Python: >=3.6
License-File: LICENSE.txt
Requires-Dist: s3-talenttech-oss ==0.0.8
